{"chunk_definitions":[{"row":9,"row_count":1,"visible":true,"expansion_state":0,"options":{"engine":"r","label":"setup","include":false},"document_id":"9294D92E","chunk_id":"csetup_chunk","chunk_label":"setup"},{"row":116,"row_count":1,"visible":true,"expansion_state":0,"options":{"engine":"r","label":"unnamed-chunk-4"},"document_id":"ADFC662D","chunk_id":"ctzuhwov1lf7r","chunk_label":"unnamed-chunk-6"},{"row":128,"row_count":1,"visible":true,"expansion_state":0,"options":{"engine":"r","label":"unnamed-chunk-3"},"document_id":"ADFC662D","chunk_id":"ccomvxfryowgg","chunk_label":"unnamed-chunk-7"},{"row":137,"row_count":1,"visible":true,"expansion_state":0,"options":{"engine":"r","label":"unnamed-chunk-4"},"document_id":"ADFC662D","chunk_id":"cuexliartax1o","chunk_label":"unnamed-chunk-8"},{"row":145,"row_count":1,"visible":true,"expansion_state":0,"options":{"engine":"r","label":"unnamed-chunk-5"},"document_id":"ADFC662D","chunk_id":"cp83yyminrgyc","chunk_label":"unnamed-chunk-9"},{"row":154,"row_count":1,"visible":true,"expansion_state":0,"options":{"engine":"r","label":"unnamed-chunk-5"},"document_id":"ADFC662D","chunk_id":"cuqgmf31i8qa5","chunk_label":"unnamed-chunk-10"},{"row":160,"row_count":1,"visible":true,"expansion_state":0,"options":{"engine":"r","label":"unnamed-chunk-6"},"document_id":"ADFC662D","chunk_id":"cav7jof8h0g4k","chunk_label":"unnamed-chunk-11"},{"row":166,"row_count":1,"visible":true,"expansion_state":0,"options":{"engine":"r","label":"unnamed-chunk-8"},"document_id":"ADFC662D","chunk_id":"ceau721frvdcu","chunk_label":"unnamed-chunk-12"},{"row":178,"row_count":1,"visible":true,"expansion_state":0,"options":{"engine":"r","results":"hide","label":"unnamed-chunk-1"},"document_id":"ADFC662D","chunk_id":"civqzyphj0dxq","chunk_label":"unnamed-chunk-13"},{"row":183,"row_count":1,"visible":true,"expansion_state":0,"options":{"engine":"r","label":"unnamed-chunk-2"},"document_id":"ADFC662D","chunk_id":"cz306mmxyupet","chunk_label":"unnamed-chunk-14"},{"row":193,"row_count":1,"visible":true,"expansion_state":0,"options":{"engine":"r","label":"unnamed-chunk-6"},"document_id":"ADFC662D","chunk_id":"cuj57410gigzh","chunk_label":"unnamed-chunk-15"},{"row":203,"row_count":1,"visible":true,"expansion_state":0,"options":{"engine":"r","results":"hide","label":"unnamed-chunk-1"},"document_id":"ADFC662D","chunk_id":"cxf36dfkzhdhu","chunk_label":"unnamed-chunk-16"},{"row":207,"row_count":1,"visible":true,"expansion_state":0,"options":{"engine":"r","label":"unnamed-chunk-2"},"document_id":"ADFC662D","chunk_id":"c8erctawk8vjf","chunk_label":"unnamed-chunk-17"},{"row":216,"row_count":1,"visible":true,"expansion_state":0,"options":{"engine":"r","label":"unnamed-chunk-7"},"document_id":"ADFC662D","chunk_id":"c00y71vw04f8r","chunk_label":"unnamed-chunk-18"},{"row":223,"row_count":1,"visible":true,"expansion_state":0,"options":{"engine":"r","label":"unnamed-chunk-3"},"document_id":"ADFC662D","chunk_id":"cuge5t8jze3by","chunk_label":"unnamed-chunk-19"},{"row":229,"row_count":1,"visible":true,"expansion_state":0,"options":{"engine":"r","label":"unnamed-chunk-8"},"document_id":"ADFC662D","chunk_id":"cgrp09a7rwryt","chunk_label":"unnamed-chunk-20"},{"row":239,"row_count":1,"visible":true,"expansion_state":0,"options":{"engine":"r","results":"hide","label":"unnamed-chunk-4"},"document_id":"ADFC662D","chunk_id":"cp046montsw2r","chunk_label":"unnamed-chunk-21"},{"row":243,"row_count":1,"visible":true,"expansion_state":0,"options":{"engine":"r","label":"unnamed-chunk-3"},"document_id":"ADFC662D","chunk_id":"cdsmapoz9dlt2","chunk_label":"unnamed-chunk-22"},{"row":251,"row_count":1,"visible":true,"expansion_state":0,"options":{"engine":"r","label":"unnamed-chunk-8"},"document_id":"ADFC662D","chunk_id":"c3yxfwzjrzwas","chunk_label":"unnamed-chunk-23"},{"row":265,"row_count":1,"visible":true,"expansion_state":0,"options":{"engine":"r","label":"unnamed-chunk-4"},"document_id":"ADFC662D","chunk_id":"cb9fclbkejg4o","chunk_label":"unnamed-chunk-25"},{"row":283,"row_count":1,"visible":true,"expansion_state":0,"options":{"engine":"r","results":"hide","label":"unnamed-chunk-9"},"document_id":"ADFC662D","chunk_id":"cb3btypa72kga","chunk_label":"unnamed-chunk-26"},{"row":286,"row_count":1,"visible":true,"expansion_state":0,"options":{"engine":"r","label":"unnamed-chunk-10"},"document_id":"ADFC662D","chunk_id":"crro25rny2zha","chunk_label":"unnamed-chunk-27"},{"row":302,"row_count":1,"visible":true,"expansion_state":0,"options":{"engine":"r","label":"unnamed-chunk-12"},"document_id":"ADFC662D","chunk_id":"cct5qh7r3dn9e","chunk_label":"unnamed-chunk-28"},{"row":308,"row_count":1,"visible":true,"expansion_state":0,"options":{"engine":"r","label":"unnamed-chunk-13"},"document_id":"ADFC662D","chunk_id":"c4j8mp84sawlc","chunk_label":"unnamed-chunk-29"},{"row":314,"row_count":1,"visible":true,"expansion_state":0,"options":{"engine":"r","label":"unnamed-chunk-11"},"document_id":"ADFC662D","chunk_id":"clka8u276wu7s","chunk_label":"unnamed-chunk-30"},{"row":320,"row_count":1,"visible":true,"expansion_state":0,"options":{"engine":"r","label":"unnamed-chunk-12"},"document_id":"ADFC662D","chunk_id":"cuotmb6t8g978","chunk_label":"unnamed-chunk-31"},{"row":331,"row_count":1,"visible":true,"expansion_state":0,"options":{"engine":"r","results":"hide","echo":false,"label":"unnamed-chunk-1"},"document_id":"ADFC662D","chunk_id":"c3jfhdf6ng1yx","chunk_label":"unnamed-chunk-32"}],"doc_write_time":1634918255,"chunk_rendered_width":528,"working_dir":null,"default_chunk_options":{"echo":true}}